MANIFEST.in
README.md
setup.py
bin/async-emitter
bin/async-subscribe
bin/sync-emitter
bin/sync-subscribe
ebosia/__init__.py
ebosia/async.py
ebosia/connection.py
ebosia/errors.py
ebosia/events.py
ebosia/fixtures.py
ebosia/sync.py
ebosia/version.py
ebosia.egg-info/PKG-INFO
ebosia.egg-info/SOURCES.txt
ebosia.egg-info/dependency_links.txt
ebosia.egg-info/entry_points.txt
ebosia.egg-info/requires.txt
ebosia.egg-info/top_level.txt