Metadata-Version: 1.0
Name: ebosia
Version: 3.15
Summary: A library for getting events throughout the system
Home-page: UNKNOWN
Author: Authentise, Inc.
Author-email: engineering@authentise.com
License: UNKNOWN
Platform: UNKNOWN
